tests/__init__.py
tests/test_anthropic_tool_use.py
tests/test_exception.py
tests/test_file_system_loader.py
tests/test_openai_tool_use.py
tool_use/__init__.py
tool_use/tools/__init__.py
tool_use/tools/anthropic_tool_use.py
tool_use/tools/openai_tool_use.py
tool_use/tools/utils.py
tool_use/yamls/anthropic_tool_use.yaml
tool_use/yamls/openai_tool_use.yaml
tool_use-0.2.1.dist-info/METADATA
tool_use-0.2.1.dist-info/WHEEL
tool_use-0.2.1.dist-info/entry_points.txt
tool_use-0.2.1.dist-info/top_level.txt
tool_use-0.2.1.dist-info/RECORD
