Metadata-Version: 2.1
Name: tool_use
Version: 0.2.1
Summary: Promptflow tool package for OpenAI/Anthropic
